Metadata-Version: 1.1
Name: powerline-notmuch
Version: 0.1
Summary: Query your notmuch database from powerline
Home-page: https://github.com/yggdr/powerline_notmuch
Author: Konstantin Schukraft
Author-email: konstantin@schukraft.org
License: ISC
Keywords: powerline notmuch email
Platform: any
Classifier: Development Status :: 4 - Beta
Classifier: Environment :: Console
Classifier: Intended Audience :: End Users/Desktop
Classifier: License :: OSI Approved :: ISC License (ISCL)
Classifier: Operating System :: POSIX
Classifier: Operating System :: Unix
Classifier: Operating System :: OS Independent
Classifier: Programming Language :: Python :: 2.6
Classifier: Programming Language :: Python :: 2.7
Classifier: Programming Language :: Python :: 3.3
Classifier: Programming Language :: Python :: 3.4
Classifier: Programming Language :: Python :: 3.5
Classifier: Programming Language :: Python :: 3.6
Classifier: Topic :: Communications :: Email
